setup.py
cdap_stream_client/__init__.py
cdap_stream_client/config.py
cdap_stream_client/serviceconnector.py
cdap_stream_client/streamclient.py
cdap_stream_client/streampromise.py
cdap_stream_client/streamwriter.py
cdap_stream_client.egg-info/PKG-INFO
cdap_stream_client.egg-info/SOURCES.txt
cdap_stream_client.egg-info/dependency_links.txt
cdap_stream_client.egg-info/requires.txt
cdap_stream_client.egg-info/top_level.txt